jax_dimenet/__init__.py
jax_dimenet/custom_space.py
jax_dimenet/dimenet.py
jax_dimenet/dimenet_basis_util.py
jax_dimenet/layers.py
jax_dimenet/sparse_graph.py
jax_dimenet-1.0.0.dist-info/LICENSE
jax_dimenet-1.0.0.dist-info/LICENSE_SHORT
jax_dimenet-1.0.0.dist-info/METADATA
jax_dimenet-1.0.0.dist-info/WHEEL
jax_dimenet-1.0.0.dist-info/top_level.txt
jax_dimenet-1.0.0.dist-info/RECORD
