Metadata-Version: 2.1
Name: jax-dimenet
Version: 1.0.0
Summary: DimeNet++ in Jax.
Home-page: https://github.com/tummfm/jax-dimenet
Author: Stephan Thaler
Author-email: stephan.thaler@tum.de
License: Apache 2.0
Platform: UNKNOWN
Classifier: Programming Language :: Python :: 3
Classifier: Programming Language :: Python :: 3.8
Classifier: Programming Language :: Python :: 3.9
Classifier: License :: OSI Approved :: Apache Software License
Classifier: Operating System :: POSIX :: Linux
Classifier: Topic :: Scientific/Engineering
Classifier: Intended Audience :: Science/Research
Classifier: Intended Audience :: Developers
Requires-Python: >=3.8
License-File: LICENSE
License-File: LICENSE_SHORT
Requires-Dist: jax (>=0.2.12)
Requires-Dist: jaxlib (>=0.1.65)
Requires-Dist: jax-md (>=0.1.13)
Requires-Dist: dm-haiku (>=0.0.4)
Requires-Dist: sympy
Requires-Dist: chex
